{"nodes": [{"id": "schema", "label": "schema.ts", "file_type": "code", "source_file": "packages/athena-webapp/convex/schema.ts", "source_location": "L1"}], "edges": [{"source": "schema", "target": "server", "relation": "imports_from", "confidence": "EXTRACTED", "source_file": "packages/athena-webapp/convex/schema.ts", "source_location": "L1", "weight": 1.0}, {"source": "schema", "target": "server", "relation": "imports_from", "confidence": "EXTRACTED", "source_file": "packages/athena-webapp/convex/schema.ts", "source_location": "L2", "weight": 1.0}, {"source": "schema", "target": "inventory", "relation": "imports_from", "confidence": "EXTRACTED", "source_file": "packages/athena-webapp/convex/schema.ts", "source_location": "L3", "weight": 1.0}, {"source": "schema", "target": "storefront", "relation": "imports_from", "confidence": "EXTRACTED", "source_file": "packages/athena-webapp/convex/schema.ts", "source_location": "L26", "weight": 1.0}, {"source": "schema", "target": "pos", "relation": "imports_from", "confidence": "EXTRACTED", "source_file": "packages/athena-webapp/convex/schema.ts", "source_location": "L48", "weight": 1.0}, {"source": "schema", "target": "possession", "relation": "imports_from", "confidence": "EXTRACTED", "source_file": "packages/athena-webapp/convex/schema.ts", "source_location": "L59", "weight": 1.0}]}