{"nodes": [{"id": "shoppingbag", "label": "ShoppingBag.tsx", "file_type": "code", "source_file": "packages/storefront-webapp/src/components/shopping-bag/ShoppingBag.tsx", "source_location": "L1"}, {"id": "shoppingbag_pendingitem", "label": "PendingItem()", "file_type": "code", "source_file": "packages/storefront-webapp/src/components/shopping-bag/ShoppingBag.tsx", "source_location": "L62"}, {"id": "shoppingbag_handleoncheckoutclick", "label": "handleOnCheckoutClick()", "file_type": "code", "source_file": "packages/storefront-webapp/src/components/shopping-bag/ShoppingBag.tsx", "source_location": "L476"}, {"id": "shoppingbag_handleclickondiscountcode", "label": "handleClickOnDiscountCode()", "file_type": "code", "source_file": "packages/storefront-webapp/src/components/shopping-bag/ShoppingBag.tsx", "source_location": "L525"}, {"id": "shoppingbag_isskuunavailable", "label": "isSkuUnavailable()", "file_type": "code", "source_file": "packages/storefront-webapp/src/components/shopping-bag/ShoppingBag.tsx", "source_location": "L537"}, {"id": "shoppingbag_handlemovetosaved", "label": "handleMoveToSaved()", "file_type": "code", "source_file": "packages/storefront-webapp/src/components/shopping-bag/ShoppingBag.tsx", "source_location": "L552"}, {"id": "shoppingbag_handledeleteitem", "label": "handleDeleteItem()", "file_type": "code", "source_file": "packages/storefront-webapp/src/components/shopping-bag/ShoppingBag.tsx", "source_location": "L566"}], "edges": [{"source": "shoppingbag", "target": "react", "relation": "imports_from", "confidence": "EXTRACTED", "source_file": "packages/storefront-webapp/src/components/shopping-bag/ShoppingBag.tsx", "source_location": "L1", "weight": 1.0}, {"source": "shoppingbag", "target": "lucide_react", "relation": "imports_from", "confidence": "EXTRACTED", "source_file": "packages/storefront-webapp/src/components/shopping-bag/ShoppingBag.tsx", "source_location": "L9", "weight": 1.0}, {"source": "shoppingbag", "target": "button", "relation": "imports_from", "confidence": "EXTRACTED", "source_file": "packages/storefront-webapp/src/components/shopping-bag/ShoppingBag.tsx", "source_location": "L26", "weight": 1.0}, {"source": "shoppingbag", "target": "storecontext", "relation": "imports_from", "confidence": "EXTRACTED", "source_file": "packages/storefront-webapp/src/components/shopping-bag/ShoppingBag.tsx", "source_location": "L27", "weight": 1.0}, {"source": "shoppingbag", "target": "react_router", "relation": "imports_from", "confidence": "EXTRACTED", "source_file": "packages/storefront-webapp/src/components/shopping-bag/ShoppingBag.tsx", "source_location": "L28", "weight": 1.0}, {"source": "shoppingbag", "target": "placeholder_png", "relation": "imports_from", "confidence": "EXTRACTED", "source_file": "packages/storefront-webapp/src/components/shopping-bag/ShoppingBag.tsx", "source_location": "L29", "weight": 1.0}, {"source": "shoppingbag", "target": "useshoppingbag", "relation": "imports_from", "confidence": "EXTRACTED", "source_file": "packages/storefront-webapp/src/components/shopping-bag/ShoppingBag.tsx", "source_location": "L30", "weight": 1.0}, {"source": "shoppingbag", "target": "webapp", "relation": "imports_from", "confidence": "EXTRACTED", "source_file": "packages/storefront-webapp/src/components/shopping-bag/ShoppingBag.tsx", "source_location": "L31", "weight": 1.0}, {"source": "shoppingbag", "target": "utils", "relation": "imports_from", "confidence": "EXTRACTED", "source_file": "packages/storefront-webapp/src/components/shopping-bag/ShoppingBag.tsx", "source_location": "L32", "weight": 1.0}, {"source": "shoppingbag", "target": "framer_motion", "relation": "imports_from", "confidence": "EXTRACTED", "source_file": "packages/storefront-webapp/src/components/shopping-bag/ShoppingBag.tsx", "source_location": "L33", "weight": 1.0}, {"source": "shoppingbag", "target": "hearticonfilled", "relation": "imports_from", "confidence": "EXTRACTED", "source_file": "packages/storefront-webapp/src/components/shopping-bag/ShoppingBag.tsx", "source_location": "L34", "weight": 1.0}, {"source": "shoppingbag", "target": "react_query", "relation": "imports_from", "confidence": "EXTRACTED", "source_file": "packages/storefront-webapp/src/components/shopping-bag/ShoppingBag.tsx", "source_location": "L35", "weight": 1.0}, {"source": "shoppingbag", "target": "loading_button", "relation": "imports_from", "confidence": "EXTRACTED", "source_file": "packages/storefront-webapp/src/components/shopping-bag/ShoppingBag.tsx", "source_location": "L36", "weight": 1.0}, {"source": "shoppingbag", "target": "empty_state", "relation": "imports_from", "confidence": "EXTRACTED", "source_file": "packages/storefront-webapp/src/components/shopping-bag/ShoppingBag.tsx", "source_location": "L37", "weight": 1.0}, {"source": "shoppingbag", "target": "fadein", "relation": "imports_from", "confidence": "EXTRACTED", "source_file": "packages/storefront-webapp/src/components/shopping-bag/ShoppingBag.tsx", "source_location": "L38", "weight": 1.0}, {"source": "shoppingbag", "target": "react_icons", "relation": "imports_from", "confidence": "EXTRACTED", "source_file": "packages/storefront-webapp/src/components/shopping-bag/ShoppingBag.tsx", "source_location": "L39", "weight": 1.0}, {"source": "shoppingbag", "target": "image_with_fallback", "relation": "imports_from", "confidence": "EXTRACTED", "source_file": "packages/storefront-webapp/src/components/shopping-bag/ShoppingBag.tsx", "source_location": "L40", "weight": 1.0}, {"source": "shoppingbag", "target": "navigationbarprovider", "relation": "imports_from", "confidence": "EXTRACTED", "source_file": "packages/storefront-webapp/src/components/shopping-bag/ShoppingBag.tsx", "source_location": "L41", "weight": 1.0}, {"source": "shoppingbag", "target": "checkout", "relation": "imports_from", "confidence": "EXTRACTED", "source_file": "packages/storefront-webapp/src/components/shopping-bag/ShoppingBag.tsx", "source_location": "L42", "weight": 1.0}, {"source": "shoppingbag", "target": "promocode", "relation": "imports_from", "confidence": "EXTRACTED", "source_file": "packages/storefront-webapp/src/components/shopping-bag/ShoppingBag.tsx", "source_location": "L43", "weight": 1.0}, {"source": "shoppingbag", "target": "storefrontjourneyevents", "relation": "imports_from", "confidence": "EXTRACTED", "source_file": "packages/storefront-webapp/src/components/shopping-bag/ShoppingBag.tsx", "source_location": "L44", "weight": 1.0}, {"source": "shoppingbag", "target": "usediscountcodealert", "relation": "imports_from", "confidence": "EXTRACTED", "source_file": "packages/storefront-webapp/src/components/shopping-bag/ShoppingBag.tsx", "source_location": "L48", "weight": 1.0}, {"source": "shoppingbag", "target": "welcomebackmodal", "relation": "imports_from", "confidence": "EXTRACTED", "source_file": "packages/storefront-webapp/src/components/shopping-bag/ShoppingBag.tsx", "source_location": "L49", "weight": 1.0}, {"source": "shoppingbag", "target": "useproductdiscount", "relation": "imports_from", "confidence": "EXTRACTED", "source_file": "packages/storefront-webapp/src/components/shopping-bag/ShoppingBag.tsx", "source_location": "L50", "weight": 1.0}, {"source": "shoppingbag", "target": "discountbadge", "relation": "imports_from", "confidence": "EXTRACTED", "source_file": "packages/storefront-webapp/src/components/shopping-bag/ShoppingBag.tsx", "source_location": "L51", "weight": 1.0}, {"source": "shoppingbag", "target": "useinventorystatus", "relation": "imports_from", "confidence": "EXTRACTED", "source_file": "packages/storefront-webapp/src/components/shopping-bag/ShoppingBag.tsx", "source_location": "L52", "weight": 1.0}, {"source": "shoppingbag", "target": "storeconfig", "relation": "imports_from", "confidence": "EXTRACTED", "source_file": "packages/storefront-webapp/src/components/shopping-bag/ShoppingBag.tsx", "source_location": "L53", "weight": 1.0}, {"source": "shoppingbag", "target": "currency", "relation": "imports_from", "confidence": "EXTRACTED", "source_file": "packages/storefront-webapp/src/components/shopping-bag/ShoppingBag.tsx", "source_location": "L54", "weight": 1.0}, {"source": "shoppingbag", "target": "usestorefrontobservability", "relation": "imports_from", "confidence": "EXTRACTED", "source_file": "packages/storefront-webapp/src/components/shopping-bag/ShoppingBag.tsx", "source_location": "L55", "weight": 1.0}, {"source": "shoppingbag", "target": "storefrontjourneyevents", "relation": "imports_from", "confidence": "EXTRACTED", "source_file": "packages/storefront-webapp/src/components/shopping-bag/ShoppingBag.tsx", "source_location": "L56", "weight": 1.0}, {"source": "shoppingbag", "target": "shoppingbag_pendingitem", "relation": "contains", "confidence": "EXTRACTED", "source_file": "packages/storefront-webapp/src/components/shopping-bag/ShoppingBag.tsx", "source_location": "L62", "weight": 1.0}, {"source": "shoppingbag", "target": "shoppingbag_handleoncheckoutclick", "relation": "contains", "confidence": "EXTRACTED", "source_file": "packages/storefront-webapp/src/components/shopping-bag/ShoppingBag.tsx", "source_location": "L476", "weight": 1.0}, {"source": "shoppingbag", "target": "shoppingbag_handleclickondiscountcode", "relation": "contains", "confidence": "EXTRACTED", "source_file": "packages/storefront-webapp/src/components/shopping-bag/ShoppingBag.tsx", "source_location": "L525", "weight": 1.0}, {"source": "shoppingbag", "target": "shoppingbag_isskuunavailable", "relation": "contains", "confidence": "EXTRACTED", "source_file": "packages/storefront-webapp/src/components/shopping-bag/ShoppingBag.tsx", "source_location": "L537", "weight": 1.0}, {"source": "shoppingbag", "target": "shoppingbag_handlemovetosaved", "relation": "contains", "confidence": "EXTRACTED", "source_file": "packages/storefront-webapp/src/components/shopping-bag/ShoppingBag.tsx", "source_location": "L552", "weight": 1.0}, {"source": "shoppingbag", "target": "shoppingbag_handledeleteitem", "relation": "contains", "confidence": "EXTRACTED", "source_file": "packages/storefront-webapp/src/components/shopping-bag/ShoppingBag.tsx", "source_location": "L566", "weight": 1.0}]}