{"nodes": [{"id": "utils", "label": "utils.ts", "file_type": "code", "source_file": "packages/storefront-webapp/src/lib/utils.ts", "source_location": "L1"}, {"id": "utils_cn", "label": "cn()", "file_type": "code", "source_file": "packages/storefront-webapp/src/lib/utils.ts", "source_location": "L9"}, {"id": "utils_geterrorforfield", "label": "getErrorForField()", "file_type": "code", "source_file": "packages/storefront-webapp/src/lib/utils.ts", "source_location": "L14"}, {"id": "utils_capitalizefirstletter", "label": "capitalizeFirstLetter()", "file_type": "code", "source_file": "packages/storefront-webapp/src/lib/utils.ts", "source_location": "L18"}, {"id": "utils_capitalizewords", "label": "capitalizeWords()", "file_type": "code", "source_file": "packages/storefront-webapp/src/lib/utils.ts", "source_location": "L23"}, {"id": "utils_slugtowords", "label": "slugToWords()", "file_type": "code", "source_file": "packages/storefront-webapp/src/lib/utils.ts", "source_location": "L31"}, {"id": "utils_currencyformatter", "label": "currencyFormatter()", "file_type": "code", "source_file": "packages/storefront-webapp/src/lib/utils.ts", "source_location": "L35"}, {"id": "utils_formatdate", "label": "formatDate()", "file_type": "code", "source_file": "packages/storefront-webapp/src/lib/utils.ts", "source_location": "L44"}, {"id": "utils_getstoredetails", "label": "getStoreDetails()", "file_type": "code", "source_file": "packages/storefront-webapp/src/lib/utils.ts", "source_location": "L53"}, {"id": "utils_enablequery", "label": "enableQuery()", "file_type": "code", "source_file": "packages/storefront-webapp/src/lib/utils.ts", "source_location": "L60"}, {"id": "utils_getrelativetime", "label": "getRelativeTime()", "file_type": "code", "source_file": "packages/storefront-webapp/src/lib/utils.ts", "source_location": "L67"}], "edges": [{"source": "utils", "target": "clsx", "relation": "imports_from", "confidence": "EXTRACTED", "source_file": "packages/storefront-webapp/src/lib/utils.ts", "source_location": "L1", "weight": 1.0}, {"source": "utils", "target": "tailwind_merge", "relation": "imports_from", "confidence": "EXTRACTED", "source_file": "packages/storefront-webapp/src/lib/utils.ts", "source_location": "L2", "weight": 1.0}, {"source": "utils", "target": "zod", "relation": "imports_from", "confidence": "EXTRACTED", "source_file": "packages/storefront-webapp/src/lib/utils.ts", "source_location": "L3", "weight": 1.0}, {"source": "utils", "target": "constants", "relation": "imports_from", "confidence": "EXTRACTED", "source_file": "packages/storefront-webapp/src/lib/utils.ts", "source_location": "L4", "weight": 1.0}, {"source": "utils", "target": "webapp", "relation": "imports_from", "confidence": "EXTRACTED", "source_file": "packages/storefront-webapp/src/lib/utils.ts", "source_location": "L5", "weight": 1.0}, {"source": "utils", "target": "utils_cn", "relation": "contains", "confidence": "EXTRACTED", "source_file": "packages/storefront-webapp/src/lib/utils.ts", "source_location": "L9", "weight": 1.0}, {"source": "utils", "target": "utils_geterrorforfield", "relation": "contains", "confidence": "EXTRACTED", "source_file": "packages/storefront-webapp/src/lib/utils.ts", "source_location": "L14", "weight": 1.0}, {"source": "utils", "target": "utils_capitalizefirstletter", "relation": "contains", "confidence": "EXTRACTED", "source_file": "packages/storefront-webapp/src/lib/utils.ts", "source_location": "L18", "weight": 1.0}, {"source": "utils", "target": "utils_capitalizewords", "relation": "contains", "confidence": "EXTRACTED", "source_file": "packages/storefront-webapp/src/lib/utils.ts", "source_location": "L23", "weight": 1.0}, {"source": "utils", "target": "utils_slugtowords", "relation": "contains", "confidence": "EXTRACTED", "source_file": "packages/storefront-webapp/src/lib/utils.ts", "source_location": "L31", "weight": 1.0}, {"source": "utils", "target": "utils_currencyformatter", "relation": "contains", "confidence": "EXTRACTED", "source_file": "packages/storefront-webapp/src/lib/utils.ts", "source_location": "L35", "weight": 1.0}, {"source": "utils", "target": "utils_formatdate", "relation": "contains", "confidence": "EXTRACTED", "source_file": "packages/storefront-webapp/src/lib/utils.ts", "source_location": "L44", "weight": 1.0}, {"source": "utils", "target": "utils_getstoredetails", "relation": "contains", "confidence": "EXTRACTED", "source_file": "packages/storefront-webapp/src/lib/utils.ts", "source_location": "L53", "weight": 1.0}, {"source": "utils", "target": "utils_enablequery", "relation": "contains", "confidence": "EXTRACTED", "source_file": "packages/storefront-webapp/src/lib/utils.ts", "source_location": "L60", "weight": 1.0}, {"source": "utils", "target": "utils_getrelativetime", "relation": "contains", "confidence": "EXTRACTED", "source_file": "packages/storefront-webapp/src/lib/utils.ts", "source_location": "L67", "weight": 1.0}]}